README.md
setup.py
ghisd/__init__.py
ghisd/hiosd.py
ghisd/sd.py
ghisd/utils.py
ghisd.egg-info/PKG-INFO
ghisd.egg-info/SOURCES.txt
ghisd.egg-info/dependency_links.txt
ghisd.egg-info/top_level.txt