Metadata-Version: 2.1
Name: ghisd
Version: 0.0.1
Summary: optimization algorithm for building a pathway map     on a energy landscape
Home-page: UNKNOWN
Author: Z.Ding
Author-email: zd1998@whu.edu.cn
License: UNKNOWN
Platform: UNKNOWN
Classifier: Programming Language :: Python :: 3
Classifier: License :: OSI Approved :: MIT License
Classifier: Operating System :: OS Independent
Requires-Python: >=3.6
